{
    "Cristiano.com": {
        "email": "Cristiano_R@gmail.com",
        "password": "VYYB(tZO%HdpFX"
    },
    "juan": {
        "email": "juan@gmail.com",
        "password": "#Mn$yCo*jkQAOKyd"
    },
    "amazon.com": {
        "email": "armazon@gmail.com",
        "password": "Rlq$r&h)DebzKWqT"
    },
    "twitter.com": {
        "email": "tw@gmail.com",
        "password": "bSGbj&AuM+B+Dmxb+h"
    },
    "otra": {
        "email": "otra@gmail.com",
        "password": ")%MIrq+cCOYPz#URJ"
    },
    "chau": {
        "email": "chau@gmail.com",
        "password": "lVf#L!bkWXg(G"
    },
    "Ebay": {
        "email": "Ebay@gmail.com",
        "password": "J!lmBTakYnKtS(x"
    }
}